{
  "student": "Student-1",
  "lesson": "lesson-2",
  "generated_at": "2026-04-16T04:29:54.637822+00:00",
  "note": "overall_score = grammar_score × (fluency_score / 100). Future: grammar_score will be mean(grammar, vocab).",
  "formula": {
    "content_score": "grammar_score (future: mean of grammar + vocab)",
    "fluency_weight": "content_score × fluency_score / 100",
    "aggregation": "mean of chunk overall_scores",
    "grammar_weights": {
      "level": 40,
      "variety": 20,
      "errors": 40
    },
    "min_chunk_words": 10,
    "min_sentence_words": 5
  },
  "aggregate": {
    "score": null,
    "score_label": "N/A",
    "color": "#9CA3AF",
    "grammar_score": 39.99,
    "fluency_score": null,
    "chunks_included": 8,
    "chunks_skipped": 0,
    "chunks_total": 8,
    "grammar_partial": false,
    "fluency_partial": true,
    "partial": true
  },
  "chunks": [
    {
      "chunk_id": 1,
      "label": "Preparing for class and studying languages including Spanish",
      "word_count": 222,
      "sentence_count": 37,
      "skipped": false,
      "skip_reason": null,
      "grammar_score": 43.8,
      "grammar_partial": false,
      "fluency_score": null,
      "fluency_sentences_included": 0,
      "fluency_fallback": false,
      "overall_score": null,
      "score_label": "N/A",
      "color": "#9CA3AF",
      "partial": true
    },
    {
      "chunk_id": 2,
      "label": "Explaining decision to speak spontaneously without preparation",
      "word_count": 211,
      "sentence_count": 38,
      "skipped": false,
      "skip_reason": null,
      "grammar_score": 41.7,
      "grammar_partial": false,
      "fluency_score": null,
      "fluency_sentences_included": 0,
      "fluency_fallback": false,
      "overall_score": null,
      "score_label": "N/A",
      "color": "#9CA3AF",
      "partial": true
    },
    {
      "chunk_id": 3,
      "label": "Practicing speaking slowly and describing daily activities",
      "word_count": 204,
      "sentence_count": 44,
      "skipped": false,
      "skip_reason": null,
      "grammar_score": 39.1,
      "grammar_partial": false,
      "fluency_score": null,
      "fluency_sentences_included": 0,
      "fluency_fallback": false,
      "overall_score": null,
      "score_label": "N/A",
      "color": "#9CA3AF",
      "partial": true
    },
    {
      "chunk_id": 4,
      "label": "Discussing lunch, healthy eating habits, and daily activities",
      "word_count": 207,
      "sentence_count": 34,
      "skipped": false,
      "skip_reason": null,
      "grammar_score": 43.0,
      "grammar_partial": false,
      "fluency_score": null,
      "fluency_sentences_included": 0,
      "fluency_fallback": false,
      "overall_score": null,
      "score_label": "N/A",
      "color": "#9CA3AF",
      "partial": true
    },
    {
      "chunk_id": 5,
      "label": "Healthy eating habits, preferences, and daily plans",
      "word_count": 208,
      "sentence_count": 38,
      "skipped": false,
      "skip_reason": null,
      "grammar_score": 51.5,
      "grammar_partial": false,
      "fluency_score": null,
      "fluency_sentences_included": 0,
      "fluency_fallback": false,
      "overall_score": null,
      "score_label": "N/A",
      "color": "#9CA3AF",
      "partial": true
    },
    {
      "chunk_id": 6,
      "label": "Daily plans, preferences, and asking teacher questions",
      "word_count": 202,
      "sentence_count": 69,
      "skipped": false,
      "skip_reason": null,
      "grammar_score": 23.7,
      "grammar_partial": false,
      "fluency_score": null,
      "fluency_sentences_included": 0,
      "fluency_fallback": false,
      "overall_score": null,
      "score_label": "N/A",
      "color": "#9CA3AF",
      "partial": true
    },
    {
      "chunk_id": 9,
      "label": "Reflecting on class, learning progress, and future goals",
      "word_count": 231,
      "sentence_count": 38,
      "skipped": false,
      "skip_reason": null,
      "grammar_score": 37.4,
      "grammar_partial": false,
      "fluency_score": null,
      "fluency_sentences_included": 0,
      "fluency_fallback": false,
      "overall_score": null,
      "score_label": "N/A",
      "color": "#9CA3AF",
      "partial": true
    },
    {
      "chunk_id": 10,
      "label": "Reflecting on learning goals and closing the class",
      "word_count": 203,
      "sentence_count": 59,
      "skipped": false,
      "skip_reason": null,
      "grammar_score": 39.7,
      "grammar_partial": false,
      "fluency_score": null,
      "fluency_sentences_included": 0,
      "fluency_fallback": false,
      "overall_score": null,
      "score_label": "N/A",
      "color": "#9CA3AF",
      "partial": true
    }
  ]
}